biolink_helper_pkg/__init__.py
biolink_helper_pkg/biolink_helper.py
biolink_helper_pkg-1.0.0.dist-info/METADATA
biolink_helper_pkg-1.0.0.dist-info/WHEEL
biolink_helper_pkg-1.0.0.dist-info/top_level.txt
biolink_helper_pkg-1.0.0.dist-info/RECORD
