Metadata-Version: 2.4
Name: biolink-helper-pkg
Version: 1.0.0
Summary: Standalone BiolinkHelper module extracted from RTX
Author-email: Your Name <you@example.com>
Requires-Python: >=3.8
Requires-Dist: networkx>=2.8
Requires-Dist: PyYAML>=6.0
Requires-Dist: requests>=2.25
